{
  "/::)": "/Emoji/emotion/0.gif",
  "/::~": "/Emoji/emotion/1.gif",
  "/::B": "/Emoji/emotion/2.gif",
  "/::|": "/Emoji/emotion/3.gif",
  "/:8-)": "/Emoji/emotion/4.gif",
  "/::<": "/Emoji/emotion/5.gif",
  "/::$": "/Emoji/emotion/6.gif",
  "/::X": "/Emoji/emotion/7.gif",
  "/::Z": "/Emoji/emotion/8.gif",
  "/::'(": "/Emoji/emotion/9.gif",
  "/::-|": "/Emoji/emotion/10.gif",
  "/::@": "/Emoji/emotion/11.gif",
  "/::P": "/Emoji/emotion/12.gif",
  "/::D": "/Emoji/emotion/13.gif",
  "/::O": "/Emoji/emotion/14.gif",
  "/::(": "/Emoji/emotion/15.gif",
  "/::+": "/Emoji/emotion/16.gif",
  "/:--b": "/Emoji/emotion/17.gif",
  "/::Q": "/Emoji/emotion/18.gif",
  "/::T": "/Emoji/emotion/19.gif",
  "/:,@P": "/Emoji/emotion/20.gif",
  "/:,@-D": "/Emoji/emotion/21.gif",
  "/::d": "/Emoji/emotion/22.gif",
  "/:,@o": "/Emoji/emotion/23.gif",
  "/::g": "/Emoji/emotion/24.gif",
  "/:|-)": "/Emoji/emotion/25.gif",
  "/::!": "/Emoji/emotion/26.gif",
  "/::L": "/Emoji/emotion/27.gif",
  "/::>": "/Emoji/emotion/28.gif",
  "/::,@": "/Emoji/emotion/29.gif",
  "/:,@f": "/Emoji/emotion/30.gif",
  "/::-S": "/Emoji/emotion/31.gif",
  "/:?": "/Emoji/emotion/32.gif",
  "/:,@x": "/Emoji/emotion/33.gif",
  "/:,@@": "/Emoji/emotion/34.gif",
  "/::8": "/Emoji/emotion/35.gif",
  "/:,@!": "/Emoji/emotion/36.gif",
  "/:!!!": "/Emoji/emotion/37.gif",
  "/:xx": "/Emoji/emotion/38.gif",
  "/:bye": "/Emoji/emotion/39.gif",
  "/:wipe": "/Emoji/emotion/40.gif",
  "/:dig": "/Emoji/emotion/41.gif",
  "/:handclap": "/Emoji/emotion/42.gif",
  "/:&-(": "/Emoji/emotion/43.gif",
  "/:B-)": "/Emoji/emotion/44.gif",
  "/:<@": "/Emoji/emotion/45.gif",
  "/:@>": "/Emoji/emotion/46.gif",
  "/::-O": "/Emoji/emotion/47.gif",
  "/:>-|": "/Emoji/emotion/48.gif",
  "/:P-(": "/Emoji/emotion/49.gif",
  "/::'|": "/Emoji/emotion/50.gif",
  "/:X-)": "/Emoji/emotion/51.gif",
  "/::*": "/Emoji/emotion/52.gif",
  "/:@x": "/Emoji/emotion/53.gif",
  "/:8*": "/Emoji/emotion/54.gif",
  "/:pd": "/Emoji/emotion/55.gif",
  "/:<W>": "/Emoji/emotion/56.gif",
  "/:beer": "/Emoji/emotion/57.gif",
  "/:basketb": "/Emoji/emotion/58.gif",
  "/:oo": "/Emoji/emotion/59.gif",
  "/:coffee": "/Emoji/emotion/60.gif",
  "/:eat": "/Emoji/emotion/61.gif",
  "/:pig": "/Emoji/emotion/62.gif",
  "/:rose": "/Emoji/emotion/63.gif",
  "/:fade": "/Emoji/emotion/64.gif",
  "/:showlove": "/Emoji/emotion/65.gif",
  "/:heart": "/Emoji/emotion/66.gif",
  "/:break": "/Emoji/emotion/67.gif",
  "/:cake": "/Emoji/emotion/68.gif",
  "/:li": "/Emoji/emotion/69.gif",
  "/:bome": "/Emoji/emotion/70.gif",
  "/:kn": "/Emoji/emotion/71.gif",
  "/:footb": "/Emoji/emotion/72.gif",
  "/:ladybug": "/Emoji/emotion/73.gif",
  "/:shit": "/Emoji/emotion/74.gif",
  "/:moon": "/Emoji/emotion/75.gif",
  "/:sun": "/Emoji/emotion/76.gif",
  "/:gift": "/Emoji/emotion/77.gif",
  "/:hug": "/Emoji/emotion/78.gif",
  "/:strong": "/Emoji/emotion/79.gif",
  "/:weak": "/Emoji/emotion/80.gif",
  "/:share": "/Emoji/emotion/81.gif",
  "/:v": "/Emoji/emotion/82.gif",
  "/:@)": "/Emoji/emotion/83.gif",
  "/:jj": "/Emoji/emotion/84.gif",
  "/:@@": "/Emoji/emotion/85.gif",
  "/:bad": "/Emoji/emotion/86.gif",
  "/:lvu": "/Emoji/emotion/87.gif",
  "/:no": "/Emoji/emotion/88.gif",
  "/:ok": "/Emoji/emotion/89.gif",
  "/:love": "/Emoji/emotion/90.gif",
  "/:<L>": "/Emoji/emotion/91.gif",
  "/:jump": "/Emoji/emotion/92.gif",
  "/:shake": "/Emoji/emotion/93.gif",
  "/:<O>": "/Emoji/emotion/94.gif",
  "/:circle": "/Emoji/emotion/95.gif",
  "/:kotow": "/Emoji/emotion/96.gif",
  "/:turn": "/Emoji/emotion/97.gif",
  "/:skip": "/Emoji/emotion/98.gif",
  "/:oY": "/Emoji/emotion/99.gif"
}
